README.md
argparse_schema.py
setup.py
argparse_schema.egg-info/PKG-INFO
argparse_schema.egg-info/SOURCES.txt
argparse_schema.egg-info/dependency_links.txt
argparse_schema.egg-info/entry_points.txt
argparse_schema.egg-info/top_level.txt