Metadata-Version: 1.0
Name: argparse-schema
Version: 0.0.3
Summary: Parse Argument with JSON Schema
Home-page: https://github.com/FebruaryBreeze/argparse-schema
Author: SF-Zhou
Author-email: sfzhou.scut@gmail.com
License: UNKNOWN
Keywords: Argument Schema
Platform: UNKNOWN
